{"updated":"2026-06-14T19:56:14.041375+03:00","updated_ts":1781456174,"channels":{"perviy":{"id":"perviy","name":"Первый канал","group":"Федеральные","site_id":"1tv"},"rossiya1":{"id":"rossiya1","name":"Россия 1","group":"Федеральные","site_id":"russia1"},"ntv":{"id":"ntv","name":"НТВ","group":"Федеральные","site_id":"ntv"},"ctc":{"id":"ctc","name":"СТС","group":"Федеральные","site_id":"ctc"},"ren":{"id":"ren","name":"РЕН ТВ","group":"Федеральные","site_id":"rentv"},"tnt":{"id":"tnt","name":"ТНТ","group":"Федеральные","site_id":"tnt"},"5tv":{"id":"5tv","name":"Пятый канал","group":"Федеральные","site_id":"5tv"},"muz":{"id":"muz","name":"МУЗ-ТВ","group":"Музыка","site_id":"muztv"},"zvez":{"id":"zvez","name":"Звезда","group":"Федеральные","site_id":"zvezda"},"match":{"id":"match","name":"Матч! ТВ","group":"Спорт","site_id":"matchtv"},"russia24":{"id":"russia24","name":"Россия 24","group":"Новости","site_id":"russia24"},"o_tv":{"id":"o_tv","name":"ОТР","group":"Федеральные","site_id":"otr"},"dom_kino":{"id":"dom_kino","name":"Дом Кино","group":"Кино","site_id":"domkino"},"nauka":{"id":"nauka","name":"Наука","group":"Познание","site_id":"nauka"},"karusel":{"id":"karusel","name":"Карусель","group":"Детские","site_id":"karusel"},"tvc":{"id":"tvc","name":"ТВ Центр","group":"Федеральные","site_id":"tvc"},"tb3":{"id":"tb3","name":"ТВ-3","group":"Развлечения","site_id":"tv3"},"sas":{"id":"sas","name":"Суббота!","group":"Развлечения","site_id":"subbota"},"chetv":{"id":"chetv","name":"Четвёрка","group":"Развлечения","site_id":"chetvertiy"},"dozhd":{"id":"dozhd","name":"Дождь","group":"Новости","site_id":"tvrain"}},"schedule":{"perviy":[{"channel":"perviy","title":"Утреннее вещание","start":1781406000,"stop":1781416800,"desc":"","genre":"","live":false},{"channel":"perviy","title":"Дневное вещание","start":1781416800,"stop":1781431200,"desc":"","genre":"","live":false},{"channel":"perviy","title":"Обеденный выпуск","start":1781431200,"stop":1781438400,"desc":"","genre":"","live":false},{"channel":"perviy","title":"Послеполуденные программы","start":1781438400,"stop":1781449200,"desc":"","genre":"","live":false},{"channel":"perviy","title":"Вечерние новости","start":1781449200,"stop":1781452800,"desc":"","genre":"","live":false},{"channel":"perviy","title":"Прайм-тайм","start":1781452800,"stop":1781461800,"desc":"","genre":"","live":true},{"channel":"perviy","title":"Ночное вещание","start":1781461800,"stop":1781470740,"desc":"","genre":"","live":false}],"rossiya1":[{"channel":"rossiya1","title":"Утреннее вещание","start":1781406000,"stop":1781416800,"desc":"","genre":"","live":false},{"channel":"rossiya1","title":"Дневное вещание","start":1781416800,"stop":1781431200,"desc":"","genre":"","live":false},{"channel":"rossiya1","title":"Обеденный выпуск","start":1781431200,"stop":1781438400,"desc":"","genre":"","live":false},{"channel":"rossiya1","title":"Послеполуденные программы","start":1781438400,"stop":1781449200,"desc":"","genre":"","live":false},{"channel":"rossiya1","title":"Вечерние новости","start":1781449200,"stop":1781452800,"desc":"","genre":"","live":false},{"channel":"rossiya1","title":"Прайм-тайм","start":1781452800,"stop":1781461800,"desc":"","genre":"","live":true},{"channel":"rossiya1","title":"Ночное вещание","start":1781461800,"stop":1781470740,"desc":"","genre":"","live":false}],"ntv":[{"channel":"ntv","title":"Утреннее вещание","start":1781406000,"stop":1781416800,"desc":"","genre":"","live":false},{"channel":"ntv","title":"Дневное вещание","start":1781416800,"stop":1781431200,"desc":"","genre":"","live":false},{"channel":"ntv","title":"Обеденный выпуск","start":1781431200,"stop":1781438400,"desc":"","genre":"","live":false},{"channel":"ntv","title":"Послеполуденные программы","start":1781438400,"stop":1781449200,"desc":"","genre":"","live":false},{"channel":"ntv","title":"Вечерние новости","start":1781449200,"stop":1781452800,"desc":"","genre":"","live":false},{"channel":"ntv","title":"Прайм-тайм","start":1781452800,"stop":1781461800,"desc":"","genre":"","live":true},{"channel":"ntv","title":"Ночное вещание","start":1781461800,"stop":1781470740,"desc":"","genre":"","live":false}],"ctc":[{"channel":"ctc","title":"Утреннее вещание","start":1781406000,"stop":1781416800,"desc":"","genre":"","live":false},{"channel":"ctc","title":"Дневное вещание","start":1781416800,"stop":1781431200,"desc":"","genre":"","live":false},{"channel":"ctc","title":"Обеденный выпуск","start":1781431200,"stop":1781438400,"desc":"","genre":"","live":false},{"channel":"ctc","title":"Послеполуденные программы","start":1781438400,"stop":1781449200,"desc":"","genre":"","live":false},{"channel":"ctc","title":"Вечерние новости","start":1781449200,"stop":1781452800,"desc":"","genre":"","live":false},{"channel":"ctc","title":"Прайм-тайм","start":1781452800,"stop":1781461800,"desc":"","genre":"","live":true},{"channel":"ctc","title":"Ночное вещание","start":1781461800,"stop":1781470740,"desc":"","genre":"","live":false}],"ren":[{"channel":"ren","title":"Утреннее вещание","start":1781406000,"stop":1781416800,"desc":"","genre":"","live":false},{"channel":"ren","title":"Дневное вещание","start":1781416800,"stop":1781431200,"desc":"","genre":"","live":false},{"channel":"ren","title":"Обеденный выпуск","start":1781431200,"stop":1781438400,"desc":"","genre":"","live":false},{"channel":"ren","title":"Послеполуденные программы","start":1781438400,"stop":1781449200,"desc":"","genre":"","live":false},{"channel":"ren","title":"Вечерние новости","start":1781449200,"stop":1781452800,"desc":"","genre":"","live":false},{"channel":"ren","title":"Прайм-тайм","start":1781452800,"stop":1781461800,"desc":"","genre":"","live":true},{"channel":"ren","title":"Ночное вещание","start":1781461800,"stop":1781470740,"desc":"","genre":"","live":false}],"tnt":[{"channel":"tnt","title":"Утреннее вещание","start":1781406000,"stop":1781416800,"desc":"","genre":"","live":false},{"channel":"tnt","title":"Дневное вещание","start":1781416800,"stop":1781431200,"desc":"","genre":"","live":false},{"channel":"tnt","title":"Обеденный выпуск","start":1781431200,"stop":1781438400,"desc":"","genre":"","live":false},{"channel":"tnt","title":"Послеполуденные программы","start":1781438400,"stop":1781449200,"desc":"","genre":"","live":false},{"channel":"tnt","title":"Вечерние новости","start":1781449200,"stop":1781452800,"desc":"","genre":"","live":false},{"channel":"tnt","title":"Прайм-тайм","start":1781452800,"stop":1781461800,"desc":"","genre":"","live":true},{"channel":"tnt","title":"Ночное вещание","start":1781461800,"stop":1781470740,"desc":"","genre":"","live":false}],"5tv":[{"channel":"5tv","title":"Утреннее вещание","start":1781406000,"stop":1781416800,"desc":"","genre":"","live":false},{"channel":"5tv","title":"Дневное вещание","start":1781416800,"stop":1781431200,"desc":"","genre":"","live":false},{"channel":"5tv","title":"Обеденный выпуск","start":1781431200,"stop":1781438400,"desc":"","genre":"","live":false},{"channel":"5tv","title":"Послеполуденные программы","start":1781438400,"stop":1781449200,"desc":"","genre":"","live":false},{"channel":"5tv","title":"Вечерние новости","start":1781449200,"stop":1781452800,"desc":"","genre":"","live":false},{"channel":"5tv","title":"Прайм-тайм","start":1781452800,"stop":1781461800,"desc":"","genre":"","live":true},{"channel":"5tv","title":"Ночное вещание","start":1781461800,"stop":1781470740,"desc":"","genre":"","live":false}],"muz":[{"channel":"muz","title":"Утреннее вещание","start":1781406000,"stop":1781416800,"desc":"","genre":"","live":false},{"channel":"muz","title":"Дневное вещание","start":1781416800,"stop":1781431200,"desc":"","genre":"","live":false},{"channel":"muz","title":"Обеденный выпуск","start":1781431200,"stop":1781438400,"desc":"","genre":"","live":false},{"channel":"muz","title":"Послеполуденные программы","start":1781438400,"stop":1781449200,"desc":"","genre":"","live":false},{"channel":"muz","title":"Вечерние новости","start":1781449200,"stop":1781452800,"desc":"","genre":"","live":false},{"channel":"muz","title":"Прайм-тайм","start":1781452800,"stop":1781461800,"desc":"","genre":"","live":true},{"channel":"muz","title":"Ночное вещание","start":1781461800,"stop":1781470740,"desc":"","genre":"","live":false}],"zvez":[{"channel":"zvez","title":"Утреннее вещание","start":1781406000,"stop":1781416800,"desc":"","genre":"","live":false},{"channel":"zvez","title":"Дневное вещание","start":1781416800,"stop":1781431200,"desc":"","genre":"","live":false},{"channel":"zvez","title":"Обеденный выпуск","start":1781431200,"stop":1781438400,"desc":"","genre":"","live":false},{"channel":"zvez","title":"Послеполуденные программы","start":1781438400,"stop":1781449200,"desc":"","genre":"","live":false},{"channel":"zvez","title":"Вечерние новости","start":1781449200,"stop":1781452800,"desc":"","genre":"","live":false},{"channel":"zvez","title":"Прайм-тайм","start":1781452800,"stop":1781461800,"desc":"","genre":"","live":true},{"channel":"zvez","title":"Ночное вещание","start":1781461800,"stop":1781470740,"desc":"","genre":"","live":false}],"match":[{"channel":"match","title":"Утреннее вещание","start":1781406000,"stop":1781416800,"desc":"","genre":"","live":false},{"channel":"match","title":"Дневное вещание","start":1781416800,"stop":1781431200,"desc":"","genre":"","live":false},{"channel":"match","title":"Обеденный выпуск","start":1781431200,"stop":1781438400,"desc":"","genre":"","live":false},{"channel":"match","title":"Послеполуденные программы","start":1781438400,"stop":1781449200,"desc":"","genre":"","live":false},{"channel":"match","title":"Вечерние новости","start":1781449200,"stop":1781452800,"desc":"","genre":"","live":false},{"channel":"match","title":"Прайм-тайм","start":1781452800,"stop":1781461800,"desc":"","genre":"","live":true},{"channel":"match","title":"Ночное вещание","start":1781461800,"stop":1781470740,"desc":"","genre":"","live":false}],"russia24":[{"channel":"russia24","title":"Утреннее вещание","start":1781406000,"stop":1781416800,"desc":"","genre":"","live":false},{"channel":"russia24","title":"Дневное вещание","start":1781416800,"stop":1781431200,"desc":"","genre":"","live":false},{"channel":"russia24","title":"Обеденный выпуск","start":1781431200,"stop":1781438400,"desc":"","genre":"","live":false},{"channel":"russia24","title":"Послеполуденные программы","start":1781438400,"stop":1781449200,"desc":"","genre":"","live":false},{"channel":"russia24","title":"Вечерние новости","start":1781449200,"stop":1781452800,"desc":"","genre":"","live":false},{"channel":"russia24","title":"Прайм-тайм","start":1781452800,"stop":1781461800,"desc":"","genre":"","live":true},{"channel":"russia24","title":"Ночное вещание","start":1781461800,"stop":1781470740,"desc":"","genre":"","live":false}],"o_tv":[{"channel":"o_tv","title":"Утреннее вещание","start":1781406000,"stop":1781416800,"desc":"","genre":"","live":false},{"channel":"o_tv","title":"Дневное вещание","start":1781416800,"stop":1781431200,"desc":"","genre":"","live":false},{"channel":"o_tv","title":"Обеденный выпуск","start":1781431200,"stop":1781438400,"desc":"","genre":"","live":false},{"channel":"o_tv","title":"Послеполуденные программы","start":1781438400,"stop":1781449200,"desc":"","genre":"","live":false},{"channel":"o_tv","title":"Вечерние новости","start":1781449200,"stop":1781452800,"desc":"","genre":"","live":false},{"channel":"o_tv","title":"Прайм-тайм","start":1781452800,"stop":1781461800,"desc":"","genre":"","live":true},{"channel":"o_tv","title":"Ночное вещание","start":1781461800,"stop":1781470740,"desc":"","genre":"","live":false}],"dom_kino":[{"channel":"dom_kino","title":"Утреннее вещание","start":1781406000,"stop":1781416800,"desc":"","genre":"","live":false},{"channel":"dom_kino","title":"Дневное вещание","start":1781416800,"stop":1781431200,"desc":"","genre":"","live":false},{"channel":"dom_kino","title":"Обеденный выпуск","start":1781431200,"stop":1781438400,"desc":"","genre":"","live":false},{"channel":"dom_kino","title":"Послеполуденные программы","start":1781438400,"stop":1781449200,"desc":"","genre":"","live":false},{"channel":"dom_kino","title":"Вечерние новости","start":1781449200,"stop":1781452800,"desc":"","genre":"","live":false},{"channel":"dom_kino","title":"Прайм-тайм","start":1781452800,"stop":1781461800,"desc":"","genre":"","live":true},{"channel":"dom_kino","title":"Ночное вещание","start":1781461800,"stop":1781470740,"desc":"","genre":"","live":false}],"nauka":[{"channel":"nauka","title":"Утреннее вещание","start":1781406000,"stop":1781416800,"desc":"","genre":"","live":false},{"channel":"nauka","title":"Дневное вещание","start":1781416800,"stop":1781431200,"desc":"","genre":"","live":false},{"channel":"nauka","title":"Обеденный выпуск","start":1781431200,"stop":1781438400,"desc":"","genre":"","live":false},{"channel":"nauka","title":"Послеполуденные программы","start":1781438400,"stop":1781449200,"desc":"","genre":"","live":false},{"channel":"nauka","title":"Вечерние новости","start":1781449200,"stop":1781452800,"desc":"","genre":"","live":false},{"channel":"nauka","title":"Прайм-тайм","start":1781452800,"stop":1781461800,"desc":"","genre":"","live":true},{"channel":"nauka","title":"Ночное вещание","start":1781461800,"stop":1781470740,"desc":"","genre":"","live":false}],"karusel":[{"channel":"karusel","title":"Утреннее вещание","start":1781406000,"stop":1781416800,"desc":"","genre":"","live":false},{"channel":"karusel","title":"Дневное вещание","start":1781416800,"stop":1781431200,"desc":"","genre":"","live":false},{"channel":"karusel","title":"Обеденный выпуск","start":1781431200,"stop":1781438400,"desc":"","genre":"","live":false},{"channel":"karusel","title":"Послеполуденные программы","start":1781438400,"stop":1781449200,"desc":"","genre":"","live":false},{"channel":"karusel","title":"Вечерние новости","start":1781449200,"stop":1781452800,"desc":"","genre":"","live":false},{"channel":"karusel","title":"Прайм-тайм","start":1781452800,"stop":1781461800,"desc":"","genre":"","live":true},{"channel":"karusel","title":"Ночное вещание","start":1781461800,"stop":1781470740,"desc":"","genre":"","live":false}],"tvc":[{"channel":"tvc","title":"Утреннее вещание","start":1781406000,"stop":1781416800,"desc":"","genre":"","live":false},{"channel":"tvc","title":"Дневное вещание","start":1781416800,"stop":1781431200,"desc":"","genre":"","live":false},{"channel":"tvc","title":"Обеденный выпуск","start":1781431200,"stop":1781438400,"desc":"","genre":"","live":false},{"channel":"tvc","title":"Послеполуденные программы","start":1781438400,"stop":1781449200,"desc":"","genre":"","live":false},{"channel":"tvc","title":"Вечерние новости","start":1781449200,"stop":1781452800,"desc":"","genre":"","live":false},{"channel":"tvc","title":"Прайм-тайм","start":1781452800,"stop":1781461800,"desc":"","genre":"","live":true},{"channel":"tvc","title":"Ночное вещание","start":1781461800,"stop":1781470740,"desc":"","genre":"","live":false}],"tb3":[{"channel":"tb3","title":"Утреннее вещание","start":1781406000,"stop":1781416800,"desc":"","genre":"","live":false},{"channel":"tb3","title":"Дневное вещание","start":1781416800,"stop":1781431200,"desc":"","genre":"","live":false},{"channel":"tb3","title":"Обеденный выпуск","start":1781431200,"stop":1781438400,"desc":"","genre":"","live":false},{"channel":"tb3","title":"Послеполуденные программы","start":1781438400,"stop":1781449200,"desc":"","genre":"","live":false},{"channel":"tb3","title":"Вечерние новости","start":1781449200,"stop":1781452800,"desc":"","genre":"","live":false},{"channel":"tb3","title":"Прайм-тайм","start":1781452800,"stop":1781461800,"desc":"","genre":"","live":true},{"channel":"tb3","title":"Ночное вещание","start":1781461800,"stop":1781470740,"desc":"","genre":"","live":false}],"sas":[{"channel":"sas","title":"Утреннее вещание","start":1781406000,"stop":1781416800,"desc":"","genre":"","live":false},{"channel":"sas","title":"Дневное вещание","start":1781416800,"stop":1781431200,"desc":"","genre":"","live":false},{"channel":"sas","title":"Обеденный выпуск","start":1781431200,"stop":1781438400,"desc":"","genre":"","live":false},{"channel":"sas","title":"Послеполуденные программы","start":1781438400,"stop":1781449200,"desc":"","genre":"","live":false},{"channel":"sas","title":"Вечерние новости","start":1781449200,"stop":1781452800,"desc":"","genre":"","live":false},{"channel":"sas","title":"Прайм-тайм","start":1781452800,"stop":1781461800,"desc":"","genre":"","live":true},{"channel":"sas","title":"Ночное вещание","start":1781461800,"stop":1781470740,"desc":"","genre":"","live":false}],"chetv":[{"channel":"chetv","title":"Утреннее вещание","start":1781406000,"stop":1781416800,"desc":"","genre":"","live":false},{"channel":"chetv","title":"Дневное вещание","start":1781416800,"stop":1781431200,"desc":"","genre":"","live":false},{"channel":"chetv","title":"Обеденный выпуск","start":1781431200,"stop":1781438400,"desc":"","genre":"","live":false},{"channel":"chetv","title":"Послеполуденные программы","start":1781438400,"stop":1781449200,"desc":"","genre":"","live":false},{"channel":"chetv","title":"Вечерние новости","start":1781449200,"stop":1781452800,"desc":"","genre":"","live":false},{"channel":"chetv","title":"Прайм-тайм","start":1781452800,"stop":1781461800,"desc":"","genre":"","live":true},{"channel":"chetv","title":"Ночное вещание","start":1781461800,"stop":1781470740,"desc":"","genre":"","live":false}],"dozhd":[{"channel":"dozhd","title":"Утреннее вещание","start":1781406000,"stop":1781416800,"desc":"","genre":"","live":false},{"channel":"dozhd","title":"Дневное вещание","start":1781416800,"stop":1781431200,"desc":"","genre":"","live":false},{"channel":"dozhd","title":"Обеденный выпуск","start":1781431200,"stop":1781438400,"desc":"","genre":"","live":false},{"channel":"dozhd","title":"Послеполуденные программы","start":1781438400,"stop":1781449200,"desc":"","genre":"","live":false},{"channel":"dozhd","title":"Вечерние новости","start":1781449200,"stop":1781452800,"desc":"","genre":"","live":false},{"channel":"dozhd","title":"Прайм-тайм","start":1781452800,"stop":1781461800,"desc":"","genre":"","live":true},{"channel":"dozhd","title":"Ночное вещание","start":1781461800,"stop":1781470740,"desc":"","genre":"","live":false}]}}